sitepop/__init__.py
sitepop/customs.py
sitepop/predefcomponents.py
sitepop/predefcss.py
sitepop/setup.py
sitepop/sitepop.py
sitepop/tester.py
sitepop-0.0.1.dist-info/METADATA
sitepop-0.0.1.dist-info/WHEEL
sitepop-0.0.1.dist-info/entry_points.txt
sitepop-0.0.1.dist-info/license_files/LICENSE
sitepop-0.0.1.dist-info/RECORD
